neuralrecommender/__init__.py
neuralrecommender/glocalk.py
neuralrecommender/model.py
neuralrecommender-0.1.0.dist-info/LICENSE
neuralrecommender-0.1.0.dist-info/METADATA
neuralrecommender-0.1.0.dist-info/WHEEL
neuralrecommender-0.1.0.dist-info/top_level.txt
neuralrecommender-0.1.0.dist-info/RECORD
