Metadata-Version: 2.1
Name: neuralrecommender
Version: 0.1.0
Summary: Simple interface for Recommendation Systems implemented with Neural Networks
Home-page: https://github.com/fleanend/NeuralRecommender
Author: fleanend (Edoardo Ferrante)
Author-email: edoardo@ferrante.ml
License: MIT
Requires-Python: >=3.7
License-File: LICENSE
Requires-Dist: numpy
Requires-Dist: torch
Requires-Dist: typing-extensions
